pagination/__init__.py
pagination/middleware.py
pagination/models.py
pagination/paginator.py
pagination/tests.py
pagination/locale/cs/LC_MESSAGES/django.mo
pagination/locale/cs/LC_MESSAGES/django.po
pagination/locale/de/LC_MESSAGES/django.mo
pagination/locale/de/LC_MESSAGES/django.po
pagination/locale/es/LC_MESSAGES/django.mo
pagination/locale/es/LC_MESSAGES/django.po
pagination/locale/fr/LC_MESSAGES/django.mo
pagination/locale/fr/LC_MESSAGES/django.po
pagination/locale/pl/LC_MESSAGES/django.mo
pagination/locale/pl/LC_MESSAGES/django.po
pagination/locale/pt/LC_MESSAGES/django.mo
pagination/locale/pt/LC_MESSAGES/django.po
pagination/locale/pt_BR/LC_MESSAGES/django.mo
pagination/locale/pt_BR/LC_MESSAGES/django.po
pagination/templates/pagination/pagination.html
pagination/templatetags/__init__.py
pagination/templatetags/pagination_tags.py
mysociety_django_pagination-1.0.9.dist-info/LICENSE.txt
mysociety_django_pagination-1.0.9.dist-info/METADATA
mysociety_django_pagination-1.0.9.dist-info/WHEEL
mysociety_django_pagination-1.0.9.dist-info/top_level.txt
mysociety_django_pagination-1.0.9.dist-info/RECORD
