Metadata-Version: 2.1
Name: mysociety-django-pagination
Version: 1.0.9
Summary: django-pagination fork with Django 1.11 support
Home-page: https://github.com/mysociety/django-pagination
Author: Eric Florenzano
Author-email: floguy@gmail.com
License: BSD
Keywords: pagination,django
Platform: UNKNOWN
Classifier: Programming Language :: Python
Classifier: Topic :: Software Development :: Libraries :: Python Modules
Classifier: Framework :: Django
Classifier: Environment :: Web Environment
Requires-Dist: future
